expression_atlas/__init__.py
expression_atlas/api.py
expression_atlas/client.py
expression_atlas/converter.py
expression_atlas/download.py
expression_atlas/exceptions.py
expression_atlas/models.py
expression_atlas/rcompat.py
expression_atlas/validation.py
expression_atlas-0.1.0.dist-info/METADATA
expression_atlas-0.1.0.dist-info/WHEEL
expression_atlas-0.1.0.dist-info/licenses/LICENSE
expression_atlas-0.1.0.dist-info/RECORD
