Metadata-Version: 2.4
Name: expression-atlas
Version: 0.1.0
Summary: Python client for searching and downloading gene expression datasets from EMBL-EBI Expression Atlas
Project-URL: Homepage, https://www.ebi.ac.uk/gxa
Project-URL: Documentation, https://github.com/ebi-gene-expression-group/expression-atlas-python
Project-URL: Repository, https://github.com/ebi-gene-expression-group/expression-atlas-python
Project-URL: Issues, https://github.com/ebi-gene-expression-group/expression-atlas-python/issues
Author-email: Expression Atlas Team <atlas-feedback@ebi.ac.uk>
License-Expression: GPL-3.0-or-later
License-File: LICENSE
Keywords: bioinformatics,ebi,expression-atlas,gene-expression,microarray,rna-seq
Classifier: Development Status :: 3 - Alpha
Classifier: Intended Audience :: Science/Research
Classifier: License :: OSI Approved :: GNU General Public License v3 or later (GPLv3+)
Classifier: Operating System :: OS Independent
Classifier: Programming Language :: Python :: 3
Classifier: Programming Language :: Python :: 3.9
Classifier: Programming Language :: Python :: 3.10
Classifier: Programming Language :: Python :: 3.11
Classifier: Programming Language :: Python :: 3.12
Classifier: Topic :: Scientific/Engineering :: Bio-Informatics
Requires-Python: >=3.9
Requires-Dist: numpy>=1.23.0
Requires-Dist: pandas>=1.5.0
Requires-Dist: requests>=2.28.0
Provides-Extra: dev
Requires-Dist: mypy>=1.0.0; extra == 'dev'
Requires-Dist: pre-commit>=3.0.0; extra == 'dev'
Requires-Dist: pytest-cov>=4.0.0; extra == 'dev'
Requires-Dist: pytest-mock>=3.10.0; extra == 'dev'
Requires-Dist: pytest>=7.0.0; extra == 'dev'
Requires-Dist: responses>=0.23.0; extra == 'dev'
Requires-Dist: ruff>=0.1.0; extra == 'dev'
Provides-Extra: docs
Requires-Dist: myst-parser>=1.0.0; extra == 'docs'
Requires-Dist: sphinx-rtd-theme>=1.2.0; extra == 'docs'
Requires-Dist: sphinx>=6.0.0; extra == 'docs'
Provides-Extra: r
Requires-Dist: rpy2>=3.5.0; extra == 'r'
